__init__.py
h5tui/__init__.py
h5tui/__main__.py
h5tui/h5tui.py
h5tui/h5tui.tcss
h5tui-0.1.12.dist-info/LICENSE
h5tui-0.1.12.dist-info/METADATA
h5tui-0.1.12.dist-info/WHEEL
h5tui-0.1.12.dist-info/entry_points.txt
h5tui-0.1.12.dist-info/top_level.txt
h5tui-0.1.12.dist-info/RECORD
