Metadata-Version: 2.1
Name: h5tui
Version: 0.1.12
Summary: TUI application for navigating and viewing HDF5 files
Author-email: Kalman Szenes <szenes.kalman@gmail.com>
License: MIT License
Project-URL: Repository, https://github.com/kszenes/h5tui
Classifier: Programming Language :: Python :: 3
Classifier: Operating System :: OS Independent
Requires-Python: >=3.8.0
License-File: LICENSE
Requires-Dist: textual
Requires-Dist: textual-plotext
Requires-Dist: h5py
Requires-Dist: numpy
Requires-Dist: pandas
